MANIFEST.in
README.md
setup.py
django_model_report.egg-info/PKG-INFO
django_model_report.egg-info/SOURCES.txt
django_model_report.egg-info/dependency_links.txt
django_model_report.egg-info/not-zip-safe
django_model_report.egg-info/requires.txt
django_model_report.egg-info/top_level.txt
model_report/__init__.py
model_report/arial10.py
model_report/export_pdf.py
model_report/report.py
model_report/urls.py
model_report/utils.py
model_report/views.py
model_report/widgets.py
model_report/highcharts/__init__.py
model_report/highcharts/base.py
model_report/highcharts/options.py
model_report/locale/es/LC_MESSAGES/django.mo
model_report/locale/es/LC_MESSAGES/django.po
model_report/static/model_report/css/datepicker.css
model_report/static/model_report/css/images/ui-bg_flat_0_aaaaaa_40x100.png
model_report/static/model_report/css/images/ui-bg_flat_0_eeeeee_40x100.png
model_report/static/model_report/css/images/ui-bg_flat_55_ffffff_40x100.png
model_report/static/model_report/css/images/ui-bg_flat_75_ffffff_40x100.png
model_report/static/model_report/css/images/ui-bg_glass_65_ffffff_1x400.png
model_report/static/model_report/css/images/ui-bg_highlight-soft_100_f6f6f6_1x100.png
model_report/static/model_report/css/images/ui-bg_highlight-soft_25_0073ea_1x100.png
model_report/static/model_report/css/images/ui-bg_highlight-soft_50_dddddd_1x100.png
model_report/static/model_report/css/images/ui-icons_0073ea_256x240.png
model_report/static/model_report/css/images/ui-icons_454545_256x240.png
model_report/static/model_report/css/images/ui-icons_666666_256x240.png
model_report/static/model_report/css/images/ui-icons_ff0084_256x240.png
model_report/static/model_report/css/images/ui-icons_ffffff_256x240.png
model_report/static/model_report/js/jquery-1.6.2.min.js
model_report/static/model_report/js/jquery-ui-1.8.16.custom.min.js
model_report/static/model_report/js/highcharts/index.htm
model_report/static/model_report/js/highcharts/examples/analytics.tsv
model_report/static/model_report/js/highcharts/examples/area-basic.htm
model_report/static/model_report/js/highcharts/examples/area-inverted.htm
model_report/static/model_report/js/highcharts/examples/area-missing.htm
model_report/static/model_report/js/highcharts/examples/area-negative.htm
