Metadata-Version: 1.1
Name: django-model-report
Version: 0.1.7
Summary: Django reports integrated with highcharts.
Home-page: https://github.com/juanpex/django-model-report
Author: juanpex
Author-email: jpma55@gmail.com
License: BSD
Keywords: django,model,report,reports,highcharts,chart,charts
Platform: UNKNOWN
Classifier: Framework :: Django
Classifier: Development Status :: 3 - Alpha
Classifier: Topic :: Internet
Classifier: License :: OSI Approved :: BSD License
Classifier: Intended Audience :: Developers
Classifier: Environment :: Web Environment
Classifier: Programming Language :: Python :: 2.5
Classifier: Programming Language :: Python :: 2.6
Classifier: Programming Language :: Python :: 2.7
